Metadata-Version: 2.4
Name: Hack4u_mah0n3
Version: 0.1.0
Summary: Una biblioteca para consultar cursos de Hack4U
Home-page: https://hack4u.io
Author: Marcelo Vázquez
Classifier: Programming Language :: Python :: 3
Classifier: License :: OSI Approved :: MIT License
Classifier: Operating System :: OS Independent
Requires-Python: >=3.7
Dynamic: author
Dynamic: classifier
Dynamic: description
Dynamic: description-content-type
Dynamic: home-page
Dynamic: requires-python
Dynamic: summary
